jaqs_fxdayu/VERSION.txt
jaqs_fxdayu/__init__.py
jaqs_fxdayu/data/__init__.py
jaqs_fxdayu/data/align.py
jaqs_fxdayu/data/built_in_funcs_docs.csv
jaqs_fxdayu/data/dataservice.py
jaqs_fxdayu/data/dataview.py
jaqs_fxdayu/data/hf_dataview.py
jaqs_fxdayu/data/py_expression_eval.py
jaqs_fxdayu/data/search_doc.py
jaqs_fxdayu/data/signal_function_mod.py
jaqs_fxdayu/data/dataapi/__init__.py
jaqs_fxdayu/data/dataapi/data_api.py
jaqs_fxdayu/data/dataapi/jrpc_py.py
jaqs_fxdayu/data/dataapi/utils.py
jaqs_fxdayu/patch_util/__init__.py
jaqs_fxdayu/patch_util/postimport.py
jaqs_fxdayu/research/__init__.py
jaqs_fxdayu/research/signaldigger/__init__.py
jaqs_fxdayu/research/signaldigger/analysis.py
jaqs_fxdayu/research/signaldigger/digger.py
jaqs_fxdayu/research/signaldigger/multi_factor.py
jaqs_fxdayu/research/signaldigger/optimizer.py
jaqs_fxdayu/research/signaldigger/performance.py
jaqs_fxdayu/research/signaldigger/plotting.py
jaqs_fxdayu/research/signaldigger/process.py
jaqs_fxdayu/research/signaldigger/signal_creator.py
jaqs_fxdayu/research/timingdigger/__init__.py
jaqs_fxdayu/research/timingdigger/digger.py
jaqs_fxdayu/research/timingdigger/performance.py
jaqs_fxdayu/research/timingdigger/plotting.py
jaqs_fxdayu/util/__init__.py
jaqs_fxdayu/util/concat.py
jaqs_fxdayu/util/dp.py
jaqs_fxdayu/util/dtutil.py
jaqs_fxdayu/util/fileio.py
jaqs_fxdayu/util/numeric.py
jaqs_fxdayu/util/pdutil.py
jaqs_fxdayu/util/profile.py
jaqs_fxdayu/util/sequence.py
jaqs_fxdayu-0.2.1.dist-info/DESCRIPTION.rst
jaqs_fxdayu-0.2.1.dist-info/METADATA
jaqs_fxdayu-0.2.1.dist-info/RECORD
jaqs_fxdayu-0.2.1.dist-info/WHEEL
jaqs_fxdayu-0.2.1.dist-info/metadata.json
jaqs_fxdayu-0.2.1.dist-info/top_level.txt
