Metadata-Version: 2.0
Name: jaqs-fxdayu
Version: 0.2.1
Summary: Open source quantitative research&trading framework, base on https://github.com/quantOS-org/JAQS
Home-page: https://github.com/xingetouzi/jaqs_fxdayu
Author: xingetouzi
Author-email: public@fxdayu.com
License: Apache License v2
Keywords: quantiatitive trading research finance
Platform: UNKNOWN
Classifier: Programming Language :: Python
Classifier: Intended Audience :: Developers
Classifier: Intended Audience :: Education
Classifier: Intended Audience :: End Users/Desktop
Classifier: Intended Audience :: Financial and Insurance Industry
Classifier: Intended Audience :: Information Technology
Classifier: Intended Audience :: Science/Research
Classifier: License :: OSI Approved :: Apache Software License
Classifier: Natural Language :: Chinese (Simplified)
Classifier: Natural Language :: English
Classifier: Operating System :: Microsoft :: Windows
Classifier: Operating System :: Unix
Classifier: Programming Language :: Python :: 3.5
Classifier: Programming Language :: Python :: 3.6
Requires-Dist: jaqs (==0.6.11)
Requires-Dist: pandas (>=0.20.0)
Requires-Dist: scipy (>=1.0.1)
Requires-Dist: sklearn (>=0.0)
Requires-Dist: statsmodels (>=0.8.0)
